pyqrp/__init__.py
pyqrp/__main__.py
pyqrp/qrautomata.py
pyqrp/qrxls.py
pyqrp-0.7.data/scripts/pyqrp
pyqrp-0.7.dist-info/LICENSE.md
pyqrp-0.7.dist-info/METADATA
pyqrp-0.7.dist-info/WHEEL
pyqrp-0.7.dist-info/top_level.txt
pyqrp-0.7.dist-info/RECORD
